ebird/checklists/__init__.py
ebird/checklists/admin.py
ebird/checklists/apps.py
ebird/checklists/loaders/__init__.py
ebird/checklists/loaders/api.py
ebird/checklists/loaders/dataset.py
ebird/checklists/loaders/mydata.py
ebird/checklists/management/__init__.py
ebird/checklists/management/commands/__init__.py
ebird/checklists/management/commands/load_api.py
ebird/checklists/management/commands/load_dataset.py
ebird/checklists/management/commands/load_mydata.py
ebird/checklists/migrations/0001_initial.py
ebird/checklists/migrations/0002_observation_date.py
ebird/checklists/migrations/0003_set_observation_date.py
ebird/checklists/migrations/0004_alter_observation_date.py
ebird/checklists/migrations/0005_rename_location_country.py
ebird/checklists/migrations/0006_add_country.py
ebird/checklists/migrations/0007_set_country.py
ebird/checklists/migrations/0008_remove_location_country_code.py
ebird/checklists/migrations/0009_add_region.py
ebird/checklists/migrations/0010_set_region.py
ebird/checklists/migrations/0011_remove_location_state_code.py
ebird/checklists/migrations/0012_add_district.py
ebird/checklists/migrations/0013_set_district.py
ebird/checklists/migrations/0014_remove_location_county_code.py
ebird/checklists/migrations/0015_add_area.py
ebird/checklists/migrations/0016_rename_checklist_area.py
ebird/checklists/migrations/0017_add_checklist_extra_location_fields.py
ebird/checklists/migrations/0018_add_observation_extra_location_fields.py
ebird/checklists/migrations/0019_set_checklist_foreign_keys.py
ebird/checklists/migrations/0020_set_observation_foreign_keys.py
ebird/checklists/migrations/0021_observation_identified.py
ebird/checklists/migrations/0022_set_identified.py
ebird/checklists/migrations/__init__.py
ebird/checklists/models/__init__.py
ebird/checklists/models/area.py
ebird/checklists/models/checklist.py
ebird/checklists/models/country.py
ebird/checklists/models/district.py
ebird/checklists/models/location.py
ebird/checklists/models/observation.py
ebird_checklists-1.1.0.dist-info/licenses/LICENSE
ebird_checklists-1.1.0.dist-info/METADATA
ebird_checklists-1.1.0.dist-info/WHEEL
ebird_checklists-1.1.0.dist-info/top_level.txt
ebird_checklists-1.1.0.dist-info/RECORD
