Metadata-Version: 2.4
Name: ebird-checklists
Version: 1.1.0
Summary: eBird Checklists is a reusable Django app for loading data from eBird into a database.
Author-email: Stuart MacKay <smackay@flagstonesoftware.com>
Keywords: checklists,Django,eBird,models,database,ebird-api,ebird basic dataset
Classifier: Development Status :: 5 - Production/Stable
Classifier: Intended Audience :: Science/Research
Classifier: Framework :: Django
Classifier: Framework :: Django :: 4.2
Classifier: Framework :: Django :: 5
Classifier: Natural Language :: English
Classifier: Programming Language :: Python :: 3
Classifier: Programming Language :: Python :: 3.8
Classifier: Programming Language :: Python :: 3.9
Classifier: Programming Language :: Python :: 3.10
Classifier: Programming Language :: Python :: 3.11
Classifier: Programming Language :: Python :: 3.12
Classifier: Topic :: Scientific/Engineering
Classifier: Topic :: Scientific/Engineering :: Information Analysis
Requires-Python: >=3.8
License-File: LICENSE
Requires-Dist: django>=4.2
Requires-Dist: ebird-api>=3.4.1
Requires-Dist: ebird-codes>=0.0.2
Requires-Dist: python-dateutil>=2.9.0.post0
Dynamic: license-file
